odoo10_addon_base_continent-10.0.1.1.0-nspkg.pth
odoo/addons/base_continent/README.rst
odoo/addons/base_continent/__init__.py
odoo/addons/base_continent/__manifest__.py
odoo/addons/base_continent/data/continent_data.xml
odoo/addons/base_continent/data/country_data.xml
odoo/addons/base_continent/i18n/base_continent.pot
odoo/addons/base_continent/i18n/de.po
odoo/addons/base_continent/i18n/es.po
odoo/addons/base_continent/i18n/eu.po
odoo/addons/base_continent/i18n/fi.po
odoo/addons/base_continent/i18n/fr.po
odoo/addons/base_continent/i18n/it.po
odoo/addons/base_continent/i18n/pt_BR.po
odoo/addons/base_continent/i18n/sl.po
odoo/addons/base_continent/migrations/10.0.1.0.1/post-migration.py
odoo/addons/base_continent/models/__init__.py
odoo/addons/base_continent/models/continent.py
odoo/addons/base_continent/models/country.py
odoo/addons/base_continent/models/partner.py
odoo/addons/base_continent/security/ir.model.access.csv
odoo/addons/base_continent/static/description/icon.png
odoo/addons/base_continent/views/continent.xml
odoo/addons/base_continent/views/country.xml
odoo/addons/base_continent/views/partner.xml
odoo10_addon_base_continent-10.0.1.1.0.dist-info/METADATA
odoo10_addon_base_continent-10.0.1.1.0.dist-info/WHEEL
odoo10_addon_base_continent-10.0.1.1.0.dist-info/namespace_packages.txt
odoo10_addon_base_continent-10.0.1.1.0.dist-info/top_level.txt
odoo10_addon_base_continent-10.0.1.1.0.dist-info/RECORD
