Metadata-Version: 2.1
Name: odoo10-addon-base-continent
Version: 10.0.1.1.0
Summary: Continent management
Home-page: UNKNOWN
Author: Camptocamp,senseFly,Amaris,Odoo Community Association (OCA)
Author-email: support@odoo-community.org
License: AGPL-3
Platform: UNKNOWN
Classifier: Programming Language :: Python
Classifier: Framework :: Odoo
Classifier: License :: OSI Approved :: GNU Affero General Public License v3
Requires-Python: ~=2.7
Requires-Dist: odoo (<10.1dev,>=10.0)
